endstone_my_plugin/__init__.py
endstone_my_plugin/my_plugin.py
endstone_my_plugin-0.1.0.dist-info/METADATA
endstone_my_plugin-0.1.0.dist-info/WHEEL
endstone_my_plugin-0.1.0.dist-info/entry_points.txt
endstone_my_plugin-0.1.0.dist-info/RECORD
