Metadata-Version: 2.4
Name: endstone-my-plugin
Version: 0.1.0
Summary: My first Python plugin for Endstone servers!
